basex/__init__.py
basex/ada.py
basex/bender.py
basex/chandler.py
basex/comments.py
basex/lygia.py
basex/models/__init__.py
basex/models/pt_core_news_md/LICENSE
basex/models/pt_core_news_md/LICENSES_SOURCES
basex/models/pt_core_news_md/MANIFEST.in
basex/models/pt_core_news_md/PKG-INFO
basex/models/pt_core_news_md/README.md
basex/models/pt_core_news_md/__init__.py
basex/models/pt_core_news_md/accuracy.json
basex/models/pt_core_news_md/config.cfg
basex/models/pt_core_news_md/meta.json
basex/models/pt_core_news_md/setup.cfg
basex/models/pt_core_news_md/setup.py
basex/models/pt_core_news_md/tokenizer
basex/models/pt_core_news_md/attribute_ruler/patterns
basex/models/pt_core_news_md/lemmatizer/cfg
basex/models/pt_core_news_md/lemmatizer/model
basex/models/pt_core_news_md/lemmatizer/trees
basex/models/pt_core_news_md/morphologizer/cfg
basex/models/pt_core_news_md/morphologizer/model
basex/models/pt_core_news_md/ner/cfg
basex/models/pt_core_news_md/ner/model
basex/models/pt_core_news_md/ner/moves
basex/models/pt_core_news_md/parser/cfg
basex/models/pt_core_news_md/parser/model
basex/models/pt_core_news_md/parser/moves
basex/models/pt_core_news_md/pt_core_news_md/LICENSE
basex/models/pt_core_news_md/pt_core_news_md/LICENSES_SOURCES
basex/models/pt_core_news_md/pt_core_news_md/README.md
basex/models/pt_core_news_md/pt_core_news_md/__init__.py
basex/models/pt_core_news_md/pt_core_news_md/accuracy.json
basex/models/pt_core_news_md/pt_core_news_md/config.cfg
basex/models/pt_core_news_md/pt_core_news_md/meta.json
basex/models/pt_core_news_md/pt_core_news_md/tokenizer
basex/models/pt_core_news_md/pt_core_news_md/attribute_ruler/patterns
basex/models/pt_core_news_md/pt_core_news_md/lemmatizer/cfg
basex/models/pt_core_news_md/pt_core_news_md/lemmatizer/model
basex/models/pt_core_news_md/pt_core_news_md/lemmatizer/trees
basex/models/pt_core_news_md/pt_core_news_md/morphologizer/cfg
basex/models/pt_core_news_md/pt_core_news_md/morphologizer/model
basex/models/pt_core_news_md/pt_core_news_md.egg-info/PKG-INFO
basex/models/pt_core_news_md/pt_core_news_md.egg-info/SOURCES.txt
basex/models/pt_core_news_md/pt_core_news_md.egg-info/dependency_links.txt
basex/models/pt_core_news_md/pt_core_news_md.egg-info/entry_points.txt
basex/models/pt_core_news_md/pt_core_news_md.egg-info/not-zip-safe
basex/models/pt_core_news_md/pt_core_news_md.egg-info/requires.txt
basex/models/pt_core_news_md/pt_core_news_md.egg-info/top_level.txt
basextools-0.0.20.dist-info/METADATA
basextools-0.0.20.dist-info/WHEEL
basextools-0.0.20.dist-info/top_level.txt
basextools-0.0.20.dist-info/RECORD
