Metadata-Version: 2.1
Name: basextools
Version: 0.0.20
Summary: Tools for EX Analysis
Home-page: UNKNOWN
Author: pin-people
Author-email: rodrigo.toledo@pinpeople.com.br
License: UNKNOWN
Platform: UNKNOWN
Requires-Dist: numpy (~=1.24.3)
Requires-Dist: pandas (~=2.0.2)
Requires-Dist: scipy (~=1.10.1)
Requires-Dist: matplotlib (~=3.7.1)
Requires-Dist: matplotlib-venn (~=0.11.9)
Requires-Dist: sentence-transformers (~=2.2.2)
Requires-Dist: scikit-learn (~=1.3.1)
Requires-Dist: plotly (~=5.15.0)
Requires-Dist: seaborn (~=0.12.2)
Requires-Dist: spacy (==3.7.2)
Requires-Dist: Unidecode (==1.3.7)
Requires-Dist: nltk (==3.8.1)
Requires-Dist: regex (==2023.10.3)
Provides-Extra: dev
Requires-Dist: pytest (>=3.7) ; extra == 'dev'
